{
  "fetchedAt": 1780351909,
  "fetchedAtIso": "2026-06-02T03:41:49.866506+05:30",
  "quotes": {
    "NIFTY": {
      "price": 23547.75,
      "prev": 23907.1504,
      "change": -359.4004,
      "pct": -1.503,
      "todaySession": {
        "open": 23654.5,
        "high": 23733.6992,
        "low": 23357.9492,
        "close": 23382.5996,
        "date": "2026-06-01"
      },
      "priorSession": {
        "open": 23902.1504,
        "high": 24002.8008,
        "low": 23484.75,
        "close": 23547.75,
        "date": "2026-05-29"
      },
      "ts": 1780351828,
      "source": "yfinance"
    },
    "BANKNIFTY": {
      "price": 54239.1992,
      "prev": 54853.8516,
      "change": -614.6523,
      "pct": -1.121,
      "todaySession": {
        "open": 54403.8516,
        "high": 54582.75,
        "low": 53470.0,
        "close": 53643.1016,
        "date": "2026-06-01"
      },
      "priorSession": {
        "open": 54748.3008,
        "high": 55184.4492,
        "low": 54116.1484,
        "close": 54239.1992,
        "date": "2026-05-29"
      },
      "ts": 1780351829,
      "source": "yfinance"
    },
    "INDIAVIX": {
      "price": 16.19,
      "prev": 14.98,
      "change": 1.21,
      "pct": 8.077,
      "todaySession": {
        "open": 16.185,
        "high": 16.9175,
        "low": 13.9125,
        "close": 16.5425,
        "date": "2026-06-01"
      },
      "priorSession": {
        "open": 14.98,
        "high": 16.55,
        "low": 14.59,
        "close": 16.19,
        "date": "2026-05-29"
      },
      "ts": 1780351830,
      "source": "yfinance"
    },
    "SP500": {
      "price": 7599.96,
      "prev": 7580.0601,
      "change": 19.8999,
      "pct": 0.263,
      "todaySession": {
        "open": 7582.29,
        "high": 7617.6602,
        "low": 7562.6099,
        "close": 7599.96,
        "date": "2026-06-01"
      },
      "priorSession": {
        "open": 7579.3301,
        "high": 7599.3799,
        "low": 7563.5498,
        "close": 7580.0601,
        "date": "2026-05-29"
      },
      "ts": 1780351830,
      "source": "yfinance"
    },
    "NASDAQ": {
      "price": 27086.8086,
      "prev": 26972.6191,
      "change": 114.1895,
      "pct": 0.423,
      "todaySession": {
        "open": 26952.5801,
        "high": 27190.207,
        "low": 26913.123,
        "close": 27086.8086,
        "date": "2026-06-01"
      },
      "priorSession": {
        "open": 26960.8398,
        "high": 27094.8008,
        "low": 26859.2695,
        "close": 26972.6191,
        "date": "2026-05-29"
      },
      "ts": 1780351831,
      "source": "yfinance"
    },
    "DOW": {
      "price": 51078.8789,
      "prev": 51032.4609,
      "change": 46.418,
      "pct": 0.091,
      "todaySession": {
        "open": 51161.1016,
        "high": 51161.1016,
        "low": 50767.3203,
        "close": 51078.8789,
        "date": "2026-06-01"
      },
      "priorSession": {
        "open": 50773.9102,
        "high": 51094.1797,
        "low": 50698.2695,
        "close": 51032.4609,
        "date": "2026-05-29"
      },
      "ts": 1780351831,
      "source": "yfinance"
    },
    "DAX": {
      "price": 25104.6992,
      "prev": 25092.25,
      "change": 12.4492,
      "pct": 0.05,
      "todaySession": {
        "open": 25083.2402,
        "high": 25301.7305,
        "low": 24901.7695,
        "close": 25003.0391,
        "date": "2026-06-01"
      },
      "priorSession": {
        "open": 25126.3496,
        "high": 25204.1309,
        "low": 25040.4492,
        "close": 25104.6992,
        "date": "2026-05-29"
      },
      "ts": 1780351832,
      "source": "yfinance"
    },
    "FTSE": {
      "price": 10338.9502,
      "prev": 10409.2998,
      "change": -70.3496,
      "pct": -0.676,
      "todaySession": {
        "open": 10409.3398,
        "high": 10409.7695,
        "low": 10288.9004,
        "close": 10338.9502,
        "date": "2026-06-01"
      },
      "priorSession": {
        "open": 10425.9004,
        "high": 10462.2002,
        "low": 10409.2998,
        "close": 10409.2998,
        "date": "2026-05-29"
      },
      "ts": 1780351833,
      "source": "yfinance"
    },
    "CAC": {
      "price": 8183.3398,
      "prev": 8188.8701,
      "change": -5.5303,
      "pct": -0.068,
      "todaySession": {
        "open": 8171.23,
        "high": 8222.2402,
        "low": 8101.1499,
        "close": 8146.5898,
        "date": "2026-06-01"
      },
      "priorSession": {
        "open": 8224.6104,
        "high": 8286.4697,
        "low": 8183.3398,
        "close": 8183.3398,
        "date": "2026-05-29"
      },
      "ts": 1780351833,
      "source": "yfinance"
    },
    "NIKKEI": {
      "price": 66329.5,
      "prev": 64693.1211,
      "change": 1636.3789,
      "pct": 2.529,
      "todaySession": {
        "open": 66363.4297,
        "high": 67231.2812,
        "low": 66244.8438,
        "close": 66934.3281,
        "date": "2026-06-01"
      },
      "priorSession": {
        "open": 65133.9688,
        "high": 66505.0234,
        "low": 65133.9688,
        "close": 66329.5,
        "date": "2026-05-29"
      },
      "ts": 1780351834,
      "source": "yfinance"
    },
    "HSI": {
      "price": 25182.3906,
      "prev": 25006.1602,
      "change": 176.2305,
      "pct": 0.705,
      "todaySession": {
        "open": 25180.0508,
        "high": 25486.7598,
        "low": 25174.3008,
        "close": 25398.1797,
        "date": "2026-06-01"
      },
      "priorSession": {
        "open": 25161.5195,
        "high": 25313.3301,
        "low": 25055.8008,
        "close": 25182.3906,
        "date": "2026-05-29"
      },
      "ts": 1780351835,
      "source": "yfinance"
    },
    "KOSPI": {
      "price": 8476.1504,
      "prev": 8185.29,
      "change": 290.8604,
      "pct": 3.553,
      "todaySession": {
        "open": 8485.6699,
        "high": 8874.1602,
        "low": 8485.6699,
        "close": 8788.3799,
        "date": "2026-06-01"
      },
      "priorSession": {
        "open": 8384.3096,
        "high": 8476.1504,
        "low": 8273.7402,
        "close": 8476.1504,
        "date": "2026-05-29"
      },
      "ts": 1780351835,
      "source": "yfinance"
    },
    "DXY": {
      "price": 99.175,
      "prev": 98.91,
      "change": 0.265,
      "pct": 0.268,
      "todaySession": {
        "open": 98.957,
        "high": 99.385,
        "low": 98.919,
        "close": 99.175,
        "date": "2026-06-01"
      },
      "priorSession": {
        "open": 99.0,
        "high": 99.19,
        "low": 98.75,
        "close": 98.91,
        "date": "2026-05-29"
      },
      "ts": 1780351836,
      "source": "yfinance"
    },
    "USDINR": {
      "price": 94.98,
      "prev": 96.0482,
      "change": -1.0682,
      "pct": -1.112,
      "todaySession": {
        "open": 94.99,
        "high": 95.16,
        "low": 94.717,
        "close": 94.98,
        "date": "2026-06-01"
      },
      "priorSession": {
        "open": 96.0482,
        "high": 96.1953,
        "low": 94.5305,
        "close": 96.0482,
        "date": "2026-05-29"
      },
      "ts": 1780351837,
      "source": "yfinance"
    },
    "EURUSD": {
      "price": 1.1637,
      "prev": 1.1653,
      "change": -0.0015,
      "pct": -0.133,
      "todaySession": {
        "open": 1.1637,
        "high": 1.1639,
        "low": 1.1636,
        "close": 1.1637,
        "date": "2026-06-01"
      },
      "priorSession": {
        "open": 1.1653,
        "high": 1.1686,
        "low": 1.1626,
        "close": 1.1653,
        "date": "2026-05-29"
      },
      "ts": 1780351837,
      "source": "yfinance"
    },
    "BRENT": {
      "price": 95.4,
      "prev": 92.05,
      "change": 3.35,
      "pct": 3.639,
      "todaySession": {
        "open": 95.4,
        "high": 95.4,
        "low": 95.4,
        "close": 95.4,
        "date": "2026-06-01"
      },
      "priorSession": {
        "open": 93.37,
        "high": 94.01,
        "low": 91.46,
        "close": 92.05,
        "date": "2026-05-29"
      },
      "ts": 1780351838,
      "source": "yfinance"
    },
    "WTI": {
      "price": 92.41,
      "prev": 87.36,
      "change": 5.05,
      "pct": 5.781,
      "todaySession": {
        "open": 92.45,
        "high": 92.54,
        "low": 92.41,
        "close": 92.41,
        "date": "2026-06-01"
      },
      "priorSession": {
        "open": 88.55,
        "high": 89.02,
        "low": 86.35,
        "close": 87.36,
        "date": "2026-05-29"
      },
      "ts": 1780351839,
      "source": "yfinance"
    },
    "GOLD": {
      "price": 4516.0,
      "prev": 4560.5,
      "change": -44.5,
      "pct": -0.976,
      "todaySession": {
        "open": 4515.7998,
        "high": 4517.8999,
        "low": 4515.7002,
        "close": 4516.0,
        "date": "2026-06-01"
      },
      "priorSession": {
        "open": 4494.0,
        "high": 4591.7998,
        "low": 4487.8999,
        "close": 4560.5,
        "date": "2026-05-29"
      },
      "ts": 1780351839,
      "source": "yfinance"
    },
    "SILVER": {
      "price": 75.205,
      "prev": 75.616,
      "change": -0.411,
      "pct": -0.544,
      "todaySession": {
        "open": 75.155,
        "high": 75.23,
        "low": 75.14,
        "close": 75.205,
        "date": "2026-06-01"
      },
      "priorSession": {
        "open": 75.52,
        "high": 75.616,
        "low": 75.115,
        "close": 75.616,
        "date": "2026-05-29"
      },
      "ts": 1780351840,
      "source": "yfinance"
    },
    "COPPER": {
      "price": 6.5675,
      "prev": 6.3595,
      "change": 0.208,
      "pct": 3.271,
      "todaySession": {
        "open": 6.5645,
        "high": 6.5705,
        "low": 6.5645,
        "close": 6.5675,
        "date": "2026-06-01"
      },
      "priorSession": {
        "open": 6.392,
        "high": 6.392,
        "low": 6.345,
        "close": 6.3595,
        "date": "2026-05-29"
      },
      "ts": 1780351840,
      "source": "yfinance"
    },
    "BTC": {
      "price": 70850.8594,
      "prev": 73579.6875,
      "change": -2728.8281,
      "pct": -3.709,
      "todaySession": {
        "open": 73568.3984,
        "high": 73874.75,
        "low": 70754.2734,
        "close": 70850.8594,
        "date": "2026-06-01"
      },
      "priorSession": {
        "open": 73753.75,
        "high": 74153.5,
        "low": 73315.0156,
        "close": 73579.6875,
        "date": "2026-05-31"
      },
      "ts": 1780351841,
      "source": "yfinance"
    },
    "ETH": {
      "price": 1985.8101,
      "prev": 2004.3416,
      "change": -18.5315,
      "pct": -0.925,
      "todaySession": {
        "open": 2004.0259,
        "high": 2014.963,
        "low": 1958.6354,
        "close": 1985.8101,
        "date": "2026-06-01"
      },
      "priorSession": {
        "open": 2019.2424,
        "high": 2034.1193,
        "low": 1991.9067,
        "close": 2004.3416,
        "date": "2026-05-31"
      },
      "ts": 1780351842,
      "source": "yfinance"
    }
  }
}